{"id":{"name":"default","location":"/Volumes/Transcend/_Projects/Project-python/Webapp-api/webapi-python/.codesight/default.json"},"buildToolConfig":{"java":{"binaryLocation":{"source":{"type":1}}},"maven":{},"gradle":{},"npm":{},"pipenv":{}},"issueSourceConfig":{"source":{"type":7,"location":"/Volumes/Transcend/_Projects/Project-python/Webapp-api/webapi-python/.codesight/default.json"},"configuredSources":[{"source":{"server":{"url":"https://poc.polaris.synopsys.com","authInfo":{},"type":4,"proxyInfo":{"ProxyConfiguration":null},"humanReadableServerName":"Polaris"},"reference":{"info":{"name":"test-python","id":"e683d54d-6e7e-445b-a4ac-31c43d14608a","displayName":"test-python","depth":2},"parent":{"info":{"name":"poc-synopsys","id":"1c40ee8c-8140-4654-a79e-44299be988b8","displayName":"poc-synopsys","depth":1,"localId":"poc.polaris.synopsys.com--poc-synopsys-1c40ee8c-8140-4654-a79e-44299be988b8"}}},"serverType":4},"Id":"3ee559b0-2758-46a7-ab3c-1e08f6626c7f"}],"activeSourceId":"3ee559b0-2758-46a7-ab3c-1e08f6626c7f"},"servers":{"coverityConnect":{"source":{"type":7,"location":"/Volumes/Transcend/_Projects/Project-python/Webapp-api/webapi-python/.codesight/default.json"},"customized":{"url":"http://10.103.3.144:8080","authInfo":{"userName":"admin","method":1},"type":1,"humanReadableServerName":"Coverity Connect"}},"blackDuck":{"source":{"type":7,"location":"/Volumes/Transcend/_Projects/Project-python/Webapp-api/webapi-python/.codesight/default.json"},"customized":{"url":"https://10.103.3.143","authInfo":{"userName":"sysadmin","method":1},"type":3,"humanReadableServerName":"Black Duck"}},"polaris":{"source":{"type":7,"location":"/Volumes/Transcend/_Projects/Project-python/Webapp-api/webapi-python/.codesight/default.json"},"customized":{"url":"https://poc.polaris.synopsys.com","authInfo":{"method":3},"type":4,"humanReadableServerName":"Polaris"},"useDefaultServerInfo":{"value":true,"source":{"type":1}}}}}